{
    "40 18 04 03": "Soldier Key",
    "50 3F 04 03": "Key to King's Passage",
    "80 B4 04 03": "Weapon Smithbox",
    "90 DB 04 03": "Armor Smithbox",
    "80 25 07 03": "Bastille Key",
    "90 4C 07 03": "Iron Key",
    "A0 73 07 03": "Forgotten Key",
    "B0 9A 07 03": "Brightstone Key",
    "C0 C1 07 03": "Antiquated Key",
    "D0 E8 07 03": "Fang Key",
    "E0 0F 08 03": "House Key",
    "F0 36 08 03": "Lenigrast's Key",
    "00 5E 08 03": "Smooth & Silky Stone",
    "88 71 08 03": "Small Smooth & Silky Stone",
    "10 85 08 03": "Rotunda Lockstone",
    "20 AC 08 03": "Giant's Kinship",
    "30 D3 08 03": "Ashen Mist Heart",
    "40 FA 08 03": "Soul of a Giant",
    "50 21 09 03": "Tseldora Den Key",
    "60 48 09 03": "Champion's Tablet",
    "70 6F 09 03": "Ladder Miniature",
    "80 96 09 03": "Soul Vessel",
    "90 BD 09 03": "Undead Lockaway Key",
    "B0 0B 0A 03": "Dull Ember",
    "C0 32 0A 03": "no data",
    "D0 59 0A 03": "Simpleton's Spice",
    "E0 80 0A 03": "Skeptic's Spice",
    "F0 A7 0A 03": "Aldia Key",
    "00 75 19 03": "Dragon Talon",
    "A0 FB 1A 03": "Heavy Iron Key",
    "40 82 1C 03": "Frozen Flower",
    "E0 08 1E 03": "Eternal Sanctum Key",
    "80 8F 1F 03": "Tower Key",
    "20 16 21 03": "Garrison Ward Key",
    "C0 9C 22 03": "no text",
    "10 60 23 03": "Dragon Stone"
}